symbiont/__init__.py
symbiont/auth.py
symbiont/client.py
symbiont/config.py
symbiont/exceptions.py
symbiont/memory.py
symbiont/models.py
symbiont/qdrant.py
symbiont_sdk-0.3.1.dist-info/licenses/LICENSE
symbiont_sdk-0.3.1.dist-info/METADATA
symbiont_sdk-0.3.1.dist-info/WHEEL
symbiont_sdk-0.3.1.dist-info/top_level.txt
symbiont_sdk-0.3.1.dist-info/RECORD
