Metadata-Version: 2.4
Name: symbiont-sdk
Version: 0.3.1
Summary: Python SDK for Symbiont platform with Tool Review and Runtime APIs
Home-page: https://github.com/thirdkeyai/symbiont-sdk-python
Author: Jascha Wanger / ThirdKey.ai
Author-email: "Jascha Wanger / ThirdKey.ai" <oss@symbiont.dev>
License: MIT
Project-URL: Homepage, https://github.com/thirdkeyai/symbiont-sdk-python
Project-URL: Documentation, https://github.com/thirdkeyai/symbiont-sdk-python#readme
Project-URL: Repository, https://github.com/thirdkeyai/symbiont-sdk-python
Project-URL: Bug Tracker, https://github.com/thirdkeyai/symbiont-sdk-python/issues
Keywords: symbiont,sdk,api,ai,agents,tool-review,runtime
Classifier: Development Status :: 4 - Beta
Classifier: Intended Audience :: Developers
Classifier: License :: OSI Approved :: MIT License
Classifier: Operating System :: OS Independent
Classifier: Programming Language :: Python :: 3
Classifier: Programming Language :: Python :: 3.8
Classifier: Programming Language :: Python :: 3.9
Classifier: Programming Language :: Python :: 3.10
Classifier: Programming Language :: Python :: 3.11
Classifier: Programming Language :: Python :: 3.12
Classifier: Topic :: Software Development :: Libraries :: Python Modules
Classifier: Topic :: Internet :: WWW/HTTP :: HTTP Servers
Classifier: Topic :: Security
Requires-Python: >=3.7
License-File: LICENSE
Requires-Dist: requests>=2.31.0
Requires-Dist: pydantic>=2.0.0
Requires-Dist: python-dotenv>=1.0.0
Requires-Dist: pyjwt>=2.8.0
Requires-Dist: cryptography>=41.0.0
Requires-Dist: pyyaml>=6.0.0
Requires-Dist: pydantic-settings>=2.0.0
Requires-Dist: redis>=5.0.0
Requires-Dist: qdrant-client>=1.7.0
Provides-Extra: dev
Requires-Dist: pytest>=7.0.0; extra == "dev"
Requires-Dist: pytest-cov>=4.0.0; extra == "dev"
Requires-Dist: ruff>=0.1.0; extra == "dev"
Requires-Dist: bandit>=1.7.0; extra == "dev"
Dynamic: author
Dynamic: home-page
Dynamic: license-file
Dynamic: requires-python
